new/2_Combinatory_logic/Nand/Nand.v
module Nand(a,b, out);
  input a;
  input b;
  output out;
  nand(out,a,b);
endmodule

new/2_Combinatory_logic/Not/Not.v
/**
 * Not gate:
 * out = not in
 */
module Not(in, out);

	input in;
	output out;
	Nand NAND(.a(in),.b(1'b1),.out(out));

endmodule

new/2_Combinatory_logic/Or/Or.v
 /**
 * Or gate:
 * out = 1 if (a == 1 or b == 1)
 *       0 otherwise
 */

module Or(a,b,out);
    input a;
   	input b;
    output out;

   	Not NOT1(.in(a),.out(na));
	Not NOT2(.in(b),.out(nb));
	Nand NAND1(.a(na),.b(nb),.out(out));

endmodule

new/2_Combinatory_logic/And/And.v
/**
 * And gate: 
 * out = 1 if (a == 1 and b == 1)
 *       0 otherwise
 */

module And(a,b,out);
    input a;
	input b;
    output out;

	Nand NAND1(.a(a),.b(b),.out(nand1));
	Not NOT(.in(nand1),.out(out));

endmodule

new/2_Combinatory_logic/Mux/Mux.v
/** 
 * Multiplexor:
 * out = a if sel == 0
 *       b otherwise
 */

module Mux(a,b,sel,out);
	input a;
   	input b;
   	input sel;
   	output out;

	Not NOT(.in(sel),.out(nsel));
	And AND1(.a(a),.b(nsel),.out(sa));
	And AND2(.a(b),.b(sel),.out(sb));
	Or OR(.a(sa),.b(sb),.out(out));

endmodule

new/2_Combinatory_logic/Mux/Mux_tb.v
module Mux_tb;
  reg a;
  reg b;
  reg sel;
  wire out;
  integer file;
  Mux MUX(.a(a), .b(b), .sel(sel), .out(out));
  initial begin
	$dumpfile("Mux_tb.vcd");
	$dumpvars(0,Mux_tb);
    file = $fopen("Mux.out", "w");
    $fwrite(file, "|   a   |   b   |  sel  |  out  |\n");
    a = 0; b = 0; sel = 0; display();
    a = 0; b = 0; sel = 1; display();
    a = 0; b = 1; sel = 0; display();
    a = 0; b = 1; sel = 1; display();
    a = 1; b = 0; sel = 0; display();
    a = 1; b = 0; sel = 1; display();
    a = 1; b = 1; sel = 0; display();
    a = 1; b = 1; sel = 1; display();
    $fclose(file);
  end
  task display;
    #1
    $fwrite(file, "|   %0b   |   %0b   |   %0b   |   %0b   |\n", a,b,sel,out);
  endtask
endmodule

new/2_Combinatory_logic/Mux/Mux_tb.vcd
$date
	Wed Apr  8 14:45:08 2020
$end
$version
	Icarus Verilog
$end
$timescale
	1s
$end
$scope module Mux_tb $end
$var wire 1 ! out $end
$var reg 1 " a $end
$var reg 1 # b $end
$var reg 1 $ sel $end
$var integer 32 % file [31:0] $end
$scope module MUX $end
$var wire 1 " a $end
$var wire 1 # b $end
$var wire 1 $ sel $end
$var wire 1 & sb $end
$var wire 1 ' sa $end
$var wire 1 ! out $end
$var wire 1 ( nsel $end
$scope module AND1 $end
$var wire 1 " a $end
$var wire 1 ' out $end
$var wire 1 ) nand1 $end
$var wire 1 ( b $end
$scope module NAND1 $end
$var wire 1 " a $end
$var wire 1 ) out $end
$var wire 1 ( b $end
$upscope $end
$scope module NOT $end
$var wire 1 ) in $end
$var wire 1 ' out $end
$scope module NAND $end
$var wire 1 ) a $end
$var wire 1 * b $end
$var wire 1 ' out $end
$upscope $end
$upscope $end
$upscope $end
$scope module AND2 $end
$var wire 1 # a $end
$var wire 1 $ b $end
$var wire 1 & out $end
$var wire 1 + nand1 $end
$scope module NAND1 $end
$var wire 1 # a $end
$var wire 1 $ b $end
$var wire 1 + out $end
$upscope $end
$scope module NOT $end
$var wire 1 + in $end
$var wire 1 & out $end
$scope module NAND $end
$var wire 1 + a $end
$var wire 1 , b $end
$var wire 1 & out $end
$upscope $end
$upscope $end
$upscope $end
$scope module NOT $end
$var wire 1 $ in $end
$var wire 1 ( out $end
$scope module NAND $end
$var wire 1 $ a $end
$var wire 1 - b $end
$var wire 1 ( out $end
$upscope $end
$upscope $end
$scope module OR $end
$var wire 1 ' a $end
$var wire 1 & b $end
$var wire 1 ! out $end
$var wire 1 . nb $end
$var wire 1 / na $end
$scope module NAND1 $end
$var wire 1 ! out $end
$var wire 1 . b $end
$var wire 1 / a $end
$upscope $end
$scope module NOT1 $end
$var wire 1 ' in $end
$var wire 1 / out $end
$scope module NAND $end
$var wire 1 ' a $end
$var wire 1 0 b $end
$var wire 1 / out $end
$upscope $end
$upscope $end
$scope module NOT2 $end
$var wire 1 & in $end
$var wire 1 . out $end
$scope module NAND $end
$var wire 1 & a $end
$var wire 1 1 b $end
$var wire 1 . out $end
$upscope $end
$upscope $end
$upscope $end
$upscope $end
$scope task display $end
$upscope $end
$upscope $end
$enddefinitions $end
#0
$dumpvars
11
10
1/
1.
1-
1,
1+
1*
1)
1(
0'
0&
b10000000000000000000000000000011 %
0$
0#
0"
0!
$end
#1
0(
1$
#2
1(
0$
1#
#3
1!
0.
1&
0+
0(
1$
#4
0/
1!
1'
1.
0)
0&
1(
1+
0$
0#
1"
#5
0!
1/
0'
1)
0(
1$
#6
1!
0/
1'
0)
1(
0$
1#
#7
1/
0.
0'
1&
1)
0+
0(
1$
